{
  "DataServices": [
    {
      "id": 1,
      "id1": "legal-1",
      "type": "legal",
      "tai": "فسخ وكالة إلكترونيًا",
      "dis": "تتيح الخدمة لأطراف الوكالة كافة إتمام عملية فسخها إلكترونياً.",
      "gah": "وزارة العدل",
      "state": "200 ريال",
      "phone": "7776543211",
      "email": "legal@gamil.com",
      "step1": "ادخل إلى البوابة.",
      "step2": "استعرض الوكالات.",
      "step3": "اختر الوكالة المطلوبة.",
      "step4": "اختر فسخها جزئياً أو كلياً."
    },
    {
      "id": 2,
      "id1": "legal-2",
      "type": "legal",
      "tai": "إطلاق سراح مؤقت",
      "dis": "تتيح الخدمة تقديم طلب للإفراج عن السجين.",
      "gah": "وزارة العدل",
      "state": "مجانا",
      "phone": "771234567",
      "email": "example@gamil.com",
      "step1": "تسجيل الدخول إلى المنصة.",
      "step2": "تعبئة نموذج الطلب.",
      "step3": "تأكيد الإرسال والمتابعة."
    },
    {
      "id": 3,
      "id1": "educational-1",
      "type": "educational",
      "tai": "طباعة شهادة",
      "dis": "إمكانية استخراج نتائج الطلاب وطباعه الشهادات.",
      "gah": "وزارة التربية والتعليم",
      "state": "50 ريال",
      "phone": "736549524",
      "email": "educational@gamil.com",
      "step1": "تسجيل الدخول.",
      "step2": "التقارير.",
      "step3": "كشوف الدرجات."
    },
    {
      "id": 4,
      "id1": "educational-2",
      "type": "educational",
      "tai": "طلب اعتذار عن الدراسة",
      "dis": "تقديم اعتذار عن الدراسة لمدة محددة.",
      "gah": "وزارة التربية والتعليم",
      "state": "350 ريال",
      "phone": "785429524",
      "email": "educational@gamil.com",
      "step1": "الدخول الموحد.",
      "step2": "سجل اسم المستخدم وكلمة المرور.",
      "step3": "أدخل نوع الحركة."
    },
    {
      "id": 5,
      "id1": "job-1",
      "type": "job",
      "tai": "تقديم طلب توظيف",
      "dis": "تقديم طلب للوظائف المتاحة.",
      "gah": "وزارة العمل",
      "state": "مجانا",
      "phone": "123456789",
      "email": "jobs@gamil.com",
      "step1": "زيارة موقع وزارة العمل.",
      "step2": "تسجيل الدخول.",
      "step3": "تعبئة نموذج الطلب."
    },
    {
      "id": 6,
      "id1": "personal-1",
      "type": "personal",
      "tai": "إصدار بطاقة هوية",
      "dis": "تقديم طلب لإصدار بطاقة هوية جديدة.",
      "gah": "وزارة الداخلية",
      "state": "150 ريال",
      "phone": "987654321",
      "email": "personal@gamil.com",
      "step1": "زيارة الموقع الرسمي.",
      "step2": "تعبئة الاستمارة.",
      "step3": "رفع المستندات المطلوبة."
    },
    {
      "id": 7,
      "id1": "health-1",
      "type": "health",
      "tai": "استفسار عن الأدوية",
      "dis": "خدمة إلكترونية للاستفسار عن الأدوية.",
      "gah": "الهيئة العامة للدواء",
      "state": "4000 ريال",
      "phone": "736549524",
      "email": "health@gamil.com",
      "step1": "زيارة الموقع الرسمي.",
      "step2": "إدخال المعلومات المطلوبة.",
      "step3": "النقر على زر إرسال."
    },
    {
      "id": 8,
      "id1": "travel-1",
      "type": "travel",
      "tai": "حجز تذاكر السفر",
      "dis": "تقديم طلب لحجز تذاكر السفر.",
      "gah": "شركة الطيران",
      "state": "300 ريال",
      "phone": "654321987",
      "email": "travel@gamil.com",
      "step1": "زيارة موقع شركة الطيران.",
      "step2": "اختيار الوجهة والتاريخ.",
      "step3": "تأكيد الحجز."
    },
    {
      "id": 9,
      "id1": "travel-2",
      "type": "travel",
      "tai": "تأشيرات السفر",
      "dis": "تقديم طلب للحصول على تأشيرة سفر.",
      "gah": "السفارة المعنية",
      "state": "500 ريال",
      "phone": "321654987",
      "email": "visa@gamil.com",
      "step1": "زيارة موقع السفارة.",
      "step2": "تعبئة نموذج الطلب.",
      "step3": "رفع المستندات المطلوبة."
    },  {
      "id": 10,
      "id1": "legal-3",
      "type": "legal",
      "tai": "تقديم شكوى قانونية",
      "dis": "خدمة لتقديم شكاوى قانونية عبر الإنترنت.",
      "gah": "وزارة العدل",
      "state": "200 ريال",
      "phone": "776543210",
      "email": "legal_complaint@gamil.com",
      "step1": "تسجيل الدخول إلى المنصة.",
      "step2": "اختيار نوع الشكوى.",
      "step3": "تعبئة النموذج وإرسال الشكوى."
    },
    {
      "id": 11,
      "id1": "educational-3",
      "type": "educational",
      "tai": "تسجيل في دورات",
      "dis": "إمكانية التسجيل في الدورات التدريبية المتاحة.",
      "gah": "وزارة التربية والتعليم",
      "state": "300 ريال",
      "phone": "765432198",
      "email": "courses@gamil.com",
      "step1": "زيارة الموقع.",
      "step2": "اختيار الدورة المطلوبة.",
      "step3": "تعبئة النموذج وإرسال الطلب."
    },
    {
      "id": 12,
      "id1": "job-2",
      "type": "job",
      "tai": "تحديث السيرة الذاتية",
      "dis": "خدمة لتحديث السيرة الذاتية على منصة التوظيف.",
      "gah": "وزارة العمل",
      "state": "مجانا",
      "phone": "321987654",
      "email": "update_cv@gamil.com",
      "step1": "الدخول إلى المنصة.",
      "step2": "اختيار السيرة الذاتية.",
      "step3": "تحديث المعلومات المطلوبة."
    },
    {
      "id": 13,
      "id1": "personal-2",
      "type": "personal",
      "tai": "تجديد جواز السفر",
      "dis": "تقديم طلب لتجديد جواز السفر.",
      "gah": "وزارة الداخلية",
      "state": "250 ريال",
      "phone": "456789123",
      "email": "renew_passport@gamil.com",
      "step1": "زيارة موقع وزارة الداخلية.",
      "step2": "تعبئة النموذج.",
      "step3": "رفع المستندات المطلوبة."
    },
    {
      "id": 14,
      "id1": "health-2",
      "type": "health",
      "tai": "استشارة طبية عن بُعد",
      "dis": "خدمة استشارات طبية عبر الإنترنت.",
      "gah": "وزارة الصحة",
      "state": "100 ريال",
      "phone": "543216789",
      "email": "health_consultation@gamil.com",
      "step1": "تسجيل الدخول إلى المنصة.",
      "step2": "اختيار الطبيب.",
      "step3": "تحديد موعد الاستشارة."
    },
    {
      "id": 15,
      "id1": "travel-3",
      "type": "travel",
      "tai": "تأجير سيارات",
      "dis": "خدمة لتأجير السيارات أثناء السفر.",
      "gah": "شركات تأجير السيارات",
      "state": "150 ريال",
      "phone": "987123456",
      "email": "car_rental@gamil.com",
      "step1": "زيارة موقع شركة التأجير.",
      "step2": "اختيار نوع السيارة.",
      "step3": "تأكيد الحجز."
    },
    {
      "id": 16,
      "id1": "legal-4",
      "type": "legal",
      "tai": "استشارة قانونية",
      "dis": "الحصول على استشارة قانونية عبر الإنترنت.",
      "gah": "مكتب محاماة",
      "state": "500 ريال",
      "phone": "765432198",
      "email": "legal_advice@gamil.com",
      "step1": "زيارة موقع المكتب.",
      "step2": "اختيار نوع الاستشارة.",
      "step3": "تعبئة النموذج وإرسال الطلب."
    },
    {
      "id": 17,
      "id1": "educational-4",
      "type": "educational",
      "tai": "تقييم الطلاب",
      "dis": "خدمة لتقييم أداء الطلاب.",
      "gah": "وزارة التربية والتعليم",
      "state": "200 ريال",
      "phone": "321456987",
      "email": "student_evaluation@gamil.com",
      "step1": "الدخول إلى المنصة.",
      "step2": "اختيار الطالب.",
      "step3": "إجراء التقييم."
    },
    {
      "id": 18,
      "id1": "job-3",
      "type": "job",
      "tai": "ورش عمل توظيف",
      "dis": "التسجيل في ورش العمل الخاصة بالتوظيف.",
      "gah": "وزارة العمل",
      "state": "مجانا",
      "phone": "456321789",
      "email": "workshops@gamil.com",
      "step1": "زيارة الموقع.",
      "step2": "اختيار الورشة.",
      "step3": "تأكيد التسجيل."
    },
    {
      "id": 19,
      "id1": "personal-3",
      "type": "personal",
      "tai": "تغيير الاسم",
      "dis": "تقديم طلب لتغيير الاسم في السجلات الرسمية.",
      "gah": "وزارة الداخلية",
      "state": "300 ريال",
      "phone": "234567891",
      "email": "change_name@gamil.com",
      "step1": "زيارة الموقع الرسمي.",
      "step2": "تعبئة الطلب.",
      "step3": "رفع المستندات المطلوبة."
    },
    {
      "id": 20,
      "id1": "health-3",
      "type": "health",
      "tai": "تسجيل لقاحات",
      "dis": "تسجيل التطعيمات الخاصة بالأفراد.",
      "gah": "وزارة الصحة",
      "state": "مجانا",
      "phone": "678901234",
      "email": "vaccine_registration@gamil.com",
      "step1": "زيارة الموقع.",
      "step2": "تسجيل الدخول.",
      "step3": "إدخال تفاصيل اللقاح."
    },
    {
      "id": 21,
      "id1": "travel-4",
      "type": "travel",
      "tai": "تخطيط الرحلات",
      "dis": "خدمة لتخطيط الرحلات السياحية.",
      "gah": "شركات السياحة",
      "state": "350 ريال",
      "phone": "876543219",
      "email": "trip_planning@gamil.com",
      "step1": "زيارة موقع الشركة.",
      "step2": "اختيار الوجهات.",
      "step3": "تأكيد الحجز."
    }
  ]
}
